---
title: "Chapter 1. Python 解释器与运行环境"
description: "深入剖析 CPython 的执行流水线、PEG 解析器、字节码结构以及虚拟环境的底层机制"
updated: "2024-03-22"
---

# Chapter 1. Python 解释器与运行环境

> **Learning Objectives**
> *   深入理解 Source -> Token -> AST -> Bytecode 的完整编译链
> *   掌握 Python 独特的词法分析机制（逻辑行与缩进处理）
> *   理解 PEG 解析器 (Python 3.9+) 与传统 LL(1) 解析器的区别
> *   能够阅读并分析 Python 字节码 (`dis` 模块)
> *   精通 `.pyc` 缓存机制与 `venv` 环境隔离原理

## 1.0 引言：不仅仅是解释器

很多开发者习惯将 Python 归类为"解释型语言"（Interpreted Language），并简单地认为它就是"逐行读取代码并执行"。这实际上是一个巨大的误解，或者说是对现代语言实现的过度简化。

标准的 CPython 解释器实际上拥有一个完整的、复杂的**编译器**前端。你的 Python 代码在被"解释"执行之前，实际上经历了一场复杂的蜕变。

### 1.0.1 厨师与食谱：一个类比
想象你在经营一家餐厅（计算机）：
*   **源代码 (.py)** 是你的食谱。
*   **CPython 解释器** 是你的厨师长。
*   **CPU** 是实际切菜和炒菜的帮厨。

如果我们是"纯解释型"（像早期的 Shell 脚本），厨师长会读一行食谱："切两个洋葱"，然后告诉帮厨去切；再读下一行："加盐"，再让帮厨去加。这种方式效率极低，因为厨师长每一步都要重新阅读和理解中文汉字。

而 CPython 的工作方式更像是一个**高效的流水线**：
1.  **预处理（编译）**：在开工前，厨师长先把复杂的中文食谱翻译成一份**简易操作清单（字节码）**。这份清单全是代号，比如 "OP_CUT_ONION" 代表切洋葱，"OP_ADD_SALT" 代表加盐。
2.  **执行（解释）**：在炒菜时，厨师长只需要拿着这份清单，飞快地指挥帮厨干活，完全不需要再纠结汉字的语法了。

这份"简易操作清单"，就是 Python 的核心秘密 —— **Bytecode（字节码）**。

---

## 1.1 CPython 编译流水线深度解析

当你运行 `python script.py` 时，解释器会启动以此下流水线：

<div data-component="PythonInterpreterFlow"></div>

### 1.1.1 Stage 1: Lexing (词法分析)

**词法分析器 (Lexer)** 的任务是将字符流 (Source Code) 转换为 **Token 流**。这不仅仅是简单的正则匹配，Python 的 Lexer 还需要处理极其特殊的缩进语法。

#### 核心机制：逻辑行与缩进处理
Python 并不直接使用 `{}` 来划分代码块，而是依靠缩进。Lexer 必须在生成 Token 时，根据缩进层级的变化，动态插入 `INDENT` 和 `DEDENT` Token。

*   **Physical Line (物理行)**: 源码文件中的一行。
*   **Logical Line (逻辑行)**: Python 解释器眼中的一行指令。
    *   Lexer 会自动将显式连接符 (`\`) 或括号内的多行内容合并为一个逻辑行。
    *   Lexer 会忽略注释和非必要的空白字符。

#### 深度透视：Tokenize 实战
让我们看看 Python 是如何"看"代码的：

```python
import tokenize
from io import BytesIO

code = b"""
def func():
    if True:
        print("Hello")
"""

tokens = list(tokenize.tokenize(BytesIO(code).readline))
for token in tokens:
    print(f"{token.type:<3} {token.string:<15} {token.start}-{token.end}")
```

**输出关键点分析**:
1.  **ENCODING**: 第一步永远是确定编码（默认 UTF-8）。
2.  **INDENT**: 当 Lexer 遇到比上一行更多的缩进时，生成此 Token。
3.  **DEDENT**: 当缩进减少时，生成此 Token。这在语法层面等同于 C 语言的 `}`。

### 1.1.2 Stage 2: Parsing (语法分析)

**解析器 (Parser)** 接收 Token 流并构建 **抽象语法树 (AST)**。

#### 革命性升级：PEG Parser (Python 3.9+)
在 Python 3.9 之前，Python 使用的是 LL(1) 解析器，这限制了语法的表达能力（例如导致了复杂的赋值表达式限制）。
从 3.9 开始，Python 切换到了 **PEG (Parsing Expression Grammar)** 解析器。

*   **LL(1) 局限性**: 只能向后看一个 Token，处理左递归非常痛苦。
*   **PEG 优势**: 拥有无限的 Lookahead 能力，能够以线性时间处理更加自然和复杂的语法结构。

#### CST vs AST
*   **CST (Concrete Syntax Tree)**: 包含所有语法细节（如括号、冒号）。旧版 Python 会先生成 CST 再转 AST。
*   **AST (Abstract Syntax Tree)**: 仅仅包含代码的逻辑结构，丢弃了无用的标点符号。现在的 CPython 直接生成 AST。

```python
import ast

code = "a = 1 + 2"
tree = ast.parse(code)
print(ast.dump(tree, indent=4))
```

### 1.1.3 Stage 3: Compiling (编译)

AST 并不能直接运行。**编译器 (Compiler)** 需要遍历 AST，将其转换为 **Code Object**。

#### 符号表 (Symbol Table)
在生成字节码之前，编译器首先会构建符号表。它会扫描整个 AST，确定每个变量的作用域（Global, Local, 或 Free/Closure）。
这就是为什么你在函数内部赋值全局变量而不声明 `global` 会报错 —— 作用域在编译期就已经确定了。

#### Code Object 结构
编译产物是一个 `code` 对象，你可以通过 `func.__code__` 访问它。它包含了：
*   `co_code`: 原始字节码 (Bytes)。
*   `co_consts`: 常量池 (None, 1, "Hello" 等)。
*   `co_varnames`: 局部变量名。
*   `co_names`: 全局变量名。

### 1.1.4 Stage 4: Interpreting (解释执行)

**PVM (Python Virtual Machine)** 是这条流水线的终点。它是一个 **基于栈 (Stack-based)** 的虚拟机。

#### 栈帧 (Stack Frame)
每当调用一个函数，VM 就会创建一个新的栈帧。栈帧包含：
*   **Value Stack**: 用于计算的临时存储区。
*   **Block Stack**: 用于管理控制流（如 try-except, loops）。
*   **Local Variables**: 当前作用域的变量。

---

## 1.2 字节码实战：读懂 VM 的指令

使用 `dis` 模块，我们可以看到 VM 实际执行的指令。这对性能优化至关重要。

### 案例 1: 循环的开销

```python
import dis

def loop_example():
    total = 0
    for i in range(3):
        total += i
    return total

dis.dis(loop_example)
```

**字节码解析**:

```text
  4           0 LOAD_CONST               1 (0)      # total = 0
              2 STORE_FAST               0 (total)

  5           4 LOAD_GLOBAL              0 (range)  # 加载 range 函数
              6 LOAD_CONST               2 (3)      # 加载参数 3
              8 CALL_FUNCTION            1          # 调用 range(3)
             10 GET_ITER                            # 获取迭代器
        >>   12 FOR_ITER                 6 (to 20)  # 开始循环 (如果结束跳到 20)
             14 STORE_FAST               1 (i)      # i = next(iterator)

  6          16 LOAD_FAST                0 (total)
             18 LOAD_FAST                1 (i)
             20 INPLACE_ADD                         # total += i
             22 STORE_FAST               0 (total)
             24 JUMP_ABSOLUTE           12          # 跳回循环开始

  7     >>   26 LOAD_FAST                0 (total)
             28 RETURN_VALUE
```

> [!NOTE]
> 观察 `LOAD_GLOBAL`。如果在循环内部调用全局函数（如 `len` 或 `range`），每次迭代都会触发字典查找。这就是为什么在极度性能敏感的代码中，我们会将 `len` 赋值给局部变量（如 `_len = len`）。

---

## 1.3 编译产物：.pyc 文件机制

`.pyc` 文件是 Python 为了通过空间换时间而设计的一种持久化缓存。

### 1.3.1 Marshaling
Code Object 需要被序列化才能存储到磁盘。Python 使用 `marshal` 模块（专用于 Python 内部对象的序列化）来完成这一步。`.pyc` 文件本质上就是 **Magic Number + Timestamp + Marshalled Code Object**。

### 1.3.2 这个 Magic Number 是什么？
文件头的前 4 个字节。它标记了 Python 的版本。如果尝试用 Python 3.10 加载 Python 3.8 编译的 `.pyc`，解释器会通过对比 Magic Number 发现不兼容并拒绝加载（或重新编译）。

---

## 1.4 环境隔离的基石：venv 底层原理

很多开发者只会用 `source activate`，但不理解这时候发生了什么。

### 1.4.1 `pyvenv.cfg` 的魔法
当你创建一个虚拟环境 `python -m venv .venv` 时，最关键的产物不是 `bin/python`，而是 `pyvenv.cfg`。

当 `.venv/bin/python` 启动时，它会：
1.  检测到同级目录下的 `pyvenv.cfg`。
2.  读取其中的 `home` 键（指向系统 Python）。
3.  **动态修改 `sys.prefix`**: 将其指向 `.venv` 目录。

### 1.4.2 `sys.prefix` 改变了什么？
`sys.prefix` 决定了标准库和第三方库 (`site-packages`) 的搜索路径。
*   **System Python**: `/usr/local/lib/python3.10/site-packages`
*   **Virtual Env**: `/.venv/lib/python3.10/site-packages`

这就是为什么你不需要管理员权限就能在虚拟环境中安装库 —— 你拥有该目录的写权限，且 Python 配置只在这个目录下查找包。

---

## Summary

*   **Lexer** 将缩进转换为 `INDENT/DEDENT` Token。
*   **Parser** (PEG) 生成 AST，并由 Compiler 生成 **Code Object**。
*   **PVM** 基于栈执行字节码，每次函数调用创建新的 **Stack Frame**。
*   **Virtual Environment** 本质上是通过修改 `sys.prefix` 来隔离 `site-packages` 路径。

下一章，我们将进入 Python 最核心的领域：**对象模型**。我们将深入探讨 `PyObject` C 结构体，揭示"为什么 Python 的整数不会溢出"以及"变量只是标签"的本质含义。
